pixel_canon/__init__.py
pixel_canon/common.py
pixel_canon/core.py
pixel_canon/utils.py
pixel_canon/backends/__init__.py
pixel_canon/backends/numpy_backend.py
pixel_canon-0.1.3.dist-info/licenses/LICENSE
pixel_canon-0.1.3.dist-info/METADATA
pixel_canon-0.1.3.dist-info/WHEEL
pixel_canon-0.1.3.dist-info/top_level.txt
pixel_canon-0.1.3.dist-info/RECORD
