Metadata-Version: 2.4
Name: pixel-canon
Version: 0.1.3
Summary: The canon for pixel data topology. A cross-language specification to define the logical layout of images.
Author-email: GolonChenroppi <golonchenroppi@gmail.com>
License: MIT License
Project-URL: Homepage, https://github.com/GolonChenroppi/pixel-canon
Project-URL: Documentation, https://github.com/GolonChenroppi/pixel-canon/blob/main/spec/v1.0.md
Project-URL: Bug Tracker, https://github.com/GolonChenroppi/pixel-canon/issues
Keywords: image,pixel,layout,numpy,pytorch,opencv,computer-vision,image-processing,hwc,chw
Classifier: Development Status :: 4 - Beta
Classifier: Programming Language :: Python :: 3
Classifier: License :: OSI Approved :: MIT License
Classifier: Operating System :: OS Independent
Classifier: Intended Audience :: Developers
Classifier: Intended Audience :: Science/Research
Classifier: Topic :: Scientific/Engineering :: Image Processing
Classifier: Topic :: Software Development :: Libraries :: Python Modules
Requires-Python: >=3.8
License-File: LICENSE
Provides-Extra: numpy
Requires-Dist: numpy; extra == "numpy"
Dynamic: license-file
